monoback.py
monoback-0.1.0.dist-info/entry_points.txt
monoback-0.1.0.dist-info/LICENSE.txt
monoback-0.1.0.dist-info/WHEEL
monoback-0.1.0.dist-info/METADATA
monoback-0.1.0.dist-info/RECORD
