Metadata-Version: 2.1
Name: monoback
Version: 0.1.0
Summary: Generate aligned CJK fallback font for your favorite monospaced font.
Author-email: Asvel <fe.asvel@gmail.com>
Requires-Python: ~=3.7
Classifier: Development Status :: 4 - Beta
Classifier: Environment :: Console
Classifier: Intended Audience :: End Users/Desktop
Classifier: Programming Language :: Python :: 3
Classifier: License :: OSI Approved :: MIT License
Classifier: Operating System :: OS Independent
Classifier: Topic :: Text Processing :: Fonts
Requires-Dist: fonttools >=4
Project-URL: Home, https://github.com/Asvel/monoback
